{
  "hero": {
    "eyebrow": "Контакты",
    "title": "Связаться",
    "description": "Доступен для экспертных консультаций по веб-инфраструктуре данных, защите от кликфрода и ИТ-предпринимательству в России. Бизнес-запросы и запросы СМИ приветствуются."
  },
  "channels": [
    {
      "id": "telegram",
      "label": "Telegram",
      "handle": "@bezsmuzi",
      "url": "https://t.me/bezsmuzi",
      "desc": "Основной канал. Быстрее всего отвечаю. Ежедневные заметки об ИТ-бизнесе.",
      "type": "russian"
    },
    {
      "id": "vk",
      "label": "ВКонтакте",
      "handle": "mkulgin",
      "url": "https://vk.com/mkulgin",
      "desc": "Личный профиль. Посты о бизнесе и сообществе.",
      "type": "russian"
    },
    {
      "id": "dzen",
      "label": "Дзен",
      "handle": "mkulgin",
      "url": "https://dzen.ru/mkulgin",
      "desc": "Длинные статьи и кейсы.",
      "type": "russian"
    }
  ],
  "availability": [
    "Экспертные консультации по веб-скрапингу и инфраструктуре данных",
    "Защита от кликфрода и анализ рекламного трафика",
    "Развитие ИТ-бизнеса в России",
    "Выступления на отраслевых мероприятиях",
    "Интервью для СМИ и редакционные материалы"
  ],
  "note": "Ответ в течение 1–2 рабочих дней. Не предлагаю менторские программы и платные курсы — это не тот формат."
}
