{
  "hero": {
    "eyebrow": "ИТ-предприниматель · Санкт-Петербург",
    "title": "Максим Кульгин",
    "subtitle": "Системы. Данные. Защита.",
    "description": "Тридцать лет в ИТ: от сетевой инженерии и корпоративной инфраструктуры — к портфелю собственных интернет-продуктов. Три инженерные книги. Строю работающие интернет-бизнесы без внешнего финансирования.",
    "cta_primary": { "label": "Читать журнал", "url": "/blog/" },
    "cta_secondary": { "label": "Проекты и кейсы", "url": "/projects/" }
  },
  "path": [
    { "year": "1990-е", "icon": "server", "icon_color": "primary", "label": "Сетевой инженер", "note": "Корпоративные сети, протоколы IP/IPX, системное администрирование" },
    { "year": "1998–2003", "icon": "book", "icon_color": "accent", "label": "Автор", "note": "3 инженерные книги по сетевой инфраструктуре" },
    { "year": "2000-е", "icon": "shopping-cart", "icon_color": "primary", "label": "Директор", "note": "Построение и управление крупным онлайн-ритейлом" },
    { "year": "2010-е", "icon": "monitor", "icon_color": "accent", "label": "Основатель SaaS", "note": "Запустил clickfraud.ru, xmldatafeed.com, offlinecrm.ru" },
    { "year": "2020-е", "icon": "layers", "icon_color": "primary", "label": "Портфель продуктов", "note": "40М+ руб./год, грант ФСИ, резидент Сколково, продукты в области данных и защиты трафика" }
  ],
  "pillars": [
    { "id": "data", "icon": "database", "icon_color": "accent", "label": "Данные и парсинг", "desc": "Веб-скрапинг, мониторинг цен, фиды данных — в промышленном масштабе" },
    { "id": "defense", "icon": "shield", "icon_color": "primary", "label": "Защита трафика", "desc": "Обнаружение кликфрода и антибот-защита для рекламодателей" },
    { "id": "systems", "icon": "network", "icon_color": "primary", "label": "Интернет-системы", "desc": "Инженерный взгляд на архитектуру и инфраструктуру продуктов" },
    { "id": "business", "icon": "trending-up", "icon_color": "accent", "label": "Рост без инвестиций", "desc": "От нуля до 40М+ руб./год — без венчурного капитала" }
  ],
  "metrics": [
    { "value": "30+", "label": "Лет в ИТ" },
    { "value": "3", "label": "Инженерные книги" },
    { "value": "40М+", "label": "Руб. выручки / год" },
    { "value": "5", "label": "Активных продуктов" }
  ],
  "quote": {
    "text": "Успешного успеха здесь нет. Только реальные цифры, настоящие ошибки и живые операционные решения.",
    "source": "Принцип канала «без смузи»"
  },
  "hero_evidence": {
    "aria_label": "Ключевые факты",
    "items": [
      { "value": "30+", "unit": "лет" },
      { "value": "7", "unit": "продуктов" },
      { "value": "3", "unit": "книги" },
      { "value": "20M+", "unit": "парсинг" }
    ]
  },
  "hero_portrait": {
    "aria_label": "Портрет Максима Кульгина"
  },
  "sections": {
    "career_path": { "eyebrow": "Карьерный путь", "title": "От сетей к экосистеме" },
    "metrics": { "aria_label": "Метрики и доказательства" },
    "pillars": { "eyebrow": "Области практики", "title": "О чём здесь пишу" },
    "blog_preview": { "title": "Свежие заметки", "aria_label": "Последние заметки" },
    "projects_preview": {
      "eyebrow": "Экосистема",
      "title": "Активные продукты",
      "link_all": "Все проекты →",
      "heading_id": "projects-preview-title",
      "aria_label": "Превью проектов",
      "preview_count": 3
    },
    "platforms": {
      "eyebrow": "Где следить",
      "title": "Публичные платформы",
      "heading_id": "platforms-title"
    }
  }
}
